fastie/__init__.py
fastie/cli.py
fastie/api/__init__.py
fastie/api/app.py
fastie/api/common.py
fastie/api/protocol.py
fastie/data/__init__.py
fastie/data/event_extraction.py
fastie/data/named_entity_recognition.py
fastie/data/relation_extraction.py
fastie/data/text_classification.py
fastie/data/uie/__init__.py
fastie/data/uie/augmenter.py
fastie/data/uie/doccano.py
fastie/data/uie/infer.py
fastie/data/uie/utils.py
fastie/extras/__init__.py
fastie/extras/adversarial.py
fastie/extras/constants.py
fastie/extras/env.py
fastie/extras/logging.py
fastie/extras/plot.py
fastie/hparams/__init__.py
fastie/hparams/data_args.py
fastie/hparams/finetune_args.py
fastie/hparams/infer_args.py
fastie/hparams/model_args.py
fastie/hparams/parser.py
fastie/metrics/__init__.py
fastie/metrics/base.py
fastie/metrics/extraction/__init__.py
fastie/metrics/extraction/precision_recall_fscore.py
fastie/metrics/extraction/score.py
fastie/metrics/extraction/span.py
fastie/models/__init__.py
fastie/models/event_extraction/__init__.py
fastie/models/event_extraction/gplinker/__init__.py
fastie/models/event_extraction/gplinker/configuration.py
fastie/models/event_extraction/gplinker/decode_utils.py
fastie/models/event_extraction/gplinker/modeling_gplinker.py
fastie/models/event_extraction/gplinker/modules.py
fastie/models/event_extraction/gplinker/tokenization.py
fastie/models/named_entity_recognition/__init__.py
fastie/models/named_entity_recognition/cnn/__init__.py
fastie/models/named_entity_recognition/cnn/configuration.py
fastie/models/named_entity_recognition/cnn/decode_utils.py
fastie/models/named_entity_recognition/cnn/modeling_cnn.py
fastie/models/named_entity_recognition/cnn/modules.py
fastie/models/named_entity_recognition/cnn/tokenization.py
fastie/models/named_entity_recognition/crf/__init__.py
fastie/models/named_entity_recognition/crf/configuration.py
fastie/models/named_entity_recognition/crf/decode_utils.py
fastie/models/named_entity_recognition/crf/modeling_crf.py
fastie-1.0.1.dev0.dist-info/LICENSE
fastie-1.0.1.dev0.dist-info/METADATA
fastie-1.0.1.dev0.dist-info/WHEEL
fastie-1.0.1.dev0.dist-info/entry_points.txt
fastie-1.0.1.dev0.dist-info/top_level.txt
fastie-1.0.1.dev0.dist-info/RECORD
