Metadata-Version: 2.1
Name: fastie
Version: 1.0.1.dev0
Summary: Easy-to-use Information Extraction Framework
Home-page: https://github.com/xusenlinzy/FastIE
Author: xusenlin
Author-email: 15797687258@163.com
License: Apache 2.0 License
Keywords: NLP,Information Extraction,NER,Text Classification,Event Extraction,transformer,pytorch,deep learning
Classifier: Development Status :: 4 - Beta
Classifier: Intended Audience :: Developers
Classifier: Intended Audience :: Education
Classifier: Intended Audience :: Science/Research
Classifier: License :: OSI Approved :: Apache Software License
Classifier: Operating System :: OS Independent
Classifier: Programming Language :: Python :: 3
Classifier: Programming Language :: Python :: 3.8
Classifier: Programming Language :: Python :: 3.9
Classifier: Programming Language :: Python :: 3.10
Classifier: Programming Language :: Python :: 3.11
Classifier: Topic :: Scientific/Engineering :: Artificial Intelligence
Requires-Python: >=3.8.0
License-File: LICENSE
Requires-Dist: datasets (>=2.21.0)
Requires-Dist: transformers (>=4.44.2)
Requires-Dist: accelerate (>=0.33.0)
